fundgz/__init__.py
fundgz/main.py
fundgz-0.1.9.dist-info/METADATA
fundgz-0.1.9.dist-info/WHEEL
fundgz-0.1.9.dist-info/entry_points.txt
fundgz-0.1.9.dist-info/top_level.txt
fundgz-0.1.9.dist-info/zip-safe
fundgz-0.1.9.dist-info/RECORD
