Metadata-Version: 2.1
Name: fundgz
Version: 0.1.9
Summary: fund search
Home-page: https://github.com/soraping/fc
Author: caoshiping
Author-email: soraping@163.com
License: MIT
Keywords: fund asynico click rich inquirer
Platform: UNKNOWN
Requires-Python: >=3.7
Requires-Dist: aiohttp
Requires-Dist: inquirer
Requires-Dist: click
Requires-Dist: rich
